dnnlib_util/__init__.py
dnnlib_util-0.3.1.dist-info/LICENSE
dnnlib_util-0.3.1.dist-info/WHEEL
dnnlib_util-0.3.1.dist-info/METADATA
dnnlib_util-0.3.1.dist-info/RECORD
